security_scanner/__init__.py
security_scanner/analyzer.py
security_scanner/bandit_test.py
security_scanner/cli.py
security_scanner/scanner.py
vyn-0.1.7.dist-info/licenses/LICENSE
vyn-0.1.7.dist-info/METADATA
vyn-0.1.7.dist-info/WHEEL
vyn-0.1.7.dist-info/entry_points.txt
vyn-0.1.7.dist-info/top_level.txt
vyn-0.1.7.dist-info/RECORD
